<?xml version="1.0" encoding="UTF-8"?> 
<java version="1.5.0_07" class="java.beans.XMLDecoder"> 
 <object class="org.strandz.core.applichousing.SdzBag"> 
  <void property="name"> 
   <string>maintainGlobal</string> 
  </void> 
  <void property="nodes"> 
   <array class="org.strandz.core.interf.Node" length="1"> 
    <void index="0"> 
     <object class="org.strandz.core.interf.Node"> 
      <void property="cascadeDelete"> 
       <boolean>false</boolean> 
      </void> 
      <void property="cell"> 
       <object id="Cell0" class="org.strandz.core.interf.Cell"> 
        <void property="attributes"> 
         <void method="add"> 
          <object class="org.strandz.core.interf.ReferenceLookupAttribute"> 
           <void property="cell"> 
            <object idref="Cell0"/> 
           </void> 
           <void property="DOField"> 
            <string>currentSeasonYear</string> 
           </void> 
           <void property="name"> 
            <string>global currentSeasonYear</string> 
           </void> 
          </object> 
         </void> 
         <void method="add"> 
          <object class="org.strandz.core.interf.ReferenceLookupAttribute"> 
           <void property="cell"> 
            <object idref="Cell0"/> 
           </void> 
           <void property="DOField"> 
            <string>currentCompetition</string> 
           </void> 
           <void property="name"> 
            <string>currentCompetition</string> 
           </void> 
          </object> 
         </void> 
        </void> 
        <void property="cells"> 
         <array class="org.strandz.core.interf.Cell" length="2"> 
          <void index="0"> 
           <object id="Cell1" class="org.strandz.core.interf.Cell"> 
            <void property="attributes"> 
             <void method="add"> 
              <object class="org.strandz.core.interf.FieldAttribute"> 
               <void property="cell"> 
                <object idref="Cell1"/> 
               </void> 
               <void property="DOField"> 
                <string>name</string> 
               </void> 
               <void property="item"> 
                <object id="JComboBox0" class="javax.swing.JComboBox"> 
                 <void property="name"> 
                  <string>cbSeasonYear</string> 
                 </void> 
                </object> 
               </void> 
               <void property="name"> 
                <string>seasonYear name</string> 
               </void> 
              </object> 
             </void> 
            </void> 
            <void id="CellArray0" property="cells"/> 
            <void property="cells"> 
             <object idref="CellArray0"/> 
            </void> 
            <void property="clazz"> 
             <object class="org.strandz.lgpl.util.Clazz"> 
              <void property="canFactory"> 
               <boolean>true</boolean> 
              </void> 
              <void property="classObject"> 
               <class>org.strandz.data.supersix.objects.SeasonYear</class> 
              </void> 
             </object> 
            </void> 
            <void property="name"> 
             <string>currentSeasonYear Lookup Cell</string> 
            </void> 
            <void property="refField"> 
             <string>currentSeasonYear</string> 
            </void> 
           </object> 
          </void> 
          <void index="1"> 
           <object id="Cell2" class="org.strandz.core.interf.Cell"> 
            <void property="attributes"> 
             <void method="add"> 
              <object class="org.strandz.core.interf.FieldAttribute"> 
               <void property="cell"> 
                <object idref="Cell2"/> 
               </void> 
               <void property="DOField"> 
                <string>name</string> 
               </void> 
               <void property="item"> 
                <object id="JComboBox1" class="javax.swing.JComboBox"> 
                 <void property="name"> 
                  <string>cbCompetition</string> 
                 </void> 
                </object> 
               </void> 
               <void property="name"> 
                <string>competition name</string> 
               </void> 
              </object> 
             </void> 
             <void method="add"> 
              <object class="org.strandz.core.interf.StemAttribute"> 
               <void property="cell"> 
                <object idref="Cell2"/> 
               </void> 
               <void property="DOField"> 
                <string>pkId</string> 
               </void> 
               <void property="name"> 
                <string>competition pkId</string> 
               </void> 
              </object> 
             </void> 
            </void> 
            <void id="CellArray1" property="cells"/> 
            <void property="cells"> 
             <object idref="CellArray1"/> 
            </void> 
            <void property="clazz"> 
             <object class="org.strandz.lgpl.util.Clazz"> 
              <void property="canFactory"> 
               <boolean>true</boolean> 
              </void> 
              <void property="classObject"> 
               <class>org.strandz.data.supersix.objects.Competition</class> 
              </void> 
             </object> 
            </void> 
            <void property="name"> 
             <string>currentCompetition Lookup Cell</string> 
            </void> 
            <void property="refField"> 
             <string>currentCompetition</string> 
            </void> 
           </object> 
          </void> 
         </array> 
        </void> 
        <void property="clazz"> 
         <object class="org.strandz.lgpl.util.Clazz"> 
          <void property="canFactory"> 
           <boolean>true</boolean> 
          </void> 
          <void property="classObject"> 
           <class>org.strandz.data.supersix.objects.Global</class> 
          </void> 
         </object> 
        </void> 
        <void property="name"> 
         <string>Global Cell</string> 
        </void> 
       </object> 
      </void> 
      <void property="editInsertsBeforeCommit"> 
       <boolean>false</boolean> 
      </void> 
      <void property="executeQuery"> 
       <boolean>false</boolean> 
      </void> 
      <void property="focusCausesNodeChange"> 
       <boolean>false</boolean> 
      </void> 
      <void id="IndependentArray0" property="independents"/> 
      <void property="independents"> 
       <object idref="IndependentArray0"/> 
      </void> 
      <void property="insert"> 
       <boolean>false</boolean> 
      </void> 
      <void property="name"> 
       <string>Global Node</string> 
      </void> 
      <void property="next"> 
       <boolean>false</boolean> 
      </void> 
      <void property="previous"> 
       <boolean>false</boolean> 
      </void> 
      <void property="remove"> 
       <boolean>false</boolean> 
      </void> 
      <void property="title"> 
       <string>Set Global Values</string> 
      </void> 
     </object> 
    </void> 
   </array> 
  </void> 
  <void property="panes"> 
   <array class="javax.swing.JComponent" length="1"> 
    <void index="0"> 
     <object class="org.strandz.view.supersix.GlobalPanel"> 
      <void method="add"> 
       <object id="JLabel0" class="javax.swing.JLabel"> 
        <void property="font"> 
         <object class="java.awt.Font"> 
          <string>Dialog</string> 
          <int>1</int> 
          <int>14</int> 
         </object> 
        </void> 
        <void property="horizontalTextPosition"> 
         <int>0</int> 
        </void> 
        <void property="opaque"> 
         <boolean>true</boolean> 
        </void> 
        <void property="text"> 
         <string>Globals</string> 
        </void> 
       </object> 
      </void> 
      <void method="add"> 
       <object id="JLabel1" class="javax.swing.JLabel"> 
        <void property="horizontalAlignment"> 
         <int>11</int> 
        </void> 
        <void property="text"> 
         <string>Current Season</string> 
        </void> 
       </object> 
      </void> 
      <void method="add"> 
       <object idref="JComboBox0"/> 
      </void> 
      <void method="add"> 
       <object id="JLabel2" class="javax.swing.JLabel"> 
        <void property="horizontalAlignment"> 
         <int>11</int> 
        </void> 
        <void property="text"> 
         <string>Current Competition</string> 
        </void> 
       </object> 
      </void> 
      <void method="add"> 
       <object idref="JComboBox1"/> 
      </void> 
      <void property="border"> 
       <object class="javax.swing.border.BevelBorder"> 
        <int>1</int> 
        <null/> 
        <null/> 
        <null/> 
        <null/> 
       </object> 
      </void> 
      <void property="cbCompetition"> 
       <object idref="JComboBox1"/> 
      </void> 
      <void property="cbSeasonYear"> 
       <object idref="JComboBox0"/> 
      </void> 
      <void property="layout"> 
       <object class="org.strandz.lgpl.tablelayout.ModernTableLayout"> 
        <void property="column"> 
         <array class="double" length="10"> 
          <void index="0"> 
           <double>20.0</double> 
          </void> 
          <void index="1"> 
           <double>0.2</double> 
          </void> 
          <void index="2"> 
           <double>15.0</double> 
          </void> 
          <void index="3"> 
           <double>0.3</double> 
          </void> 
          <void index="4"> 
           <double>7.0</double> 
          </void> 
          <void index="5"> 
           <double>0.2</double> 
          </void> 
          <void index="6"> 
           <double>15.0</double> 
          </void> 
          <void index="7"> 
           <double>0.3</double> 
          </void> 
          <void index="8"> 
           <double>-1.0</double> 
          </void> 
          <void index="9"> 
           <double>20.0</double> 
          </void> 
         </array> 
        </void> 
        <void property="row"> 
         <array class="double" length="10"> 
          <void index="0"> 
           <double>-1.0</double> 
          </void> 
          <void index="1"> 
           <double>23.0</double> 
          </void> 
          <void index="2"> 
           <double>2.0</double> 
          </void> 
          <void index="3"> 
           <double>23.0</double> 
          </void> 
          <void index="4"> 
           <double>2.0</double> 
          </void> 
          <void index="5"> 
           <double>23.0</double> 
          </void> 
          <void index="6"> 
           <double>2.0</double> 
          </void> 
          <void index="7"> 
           <double>23.0</double> 
          </void> 
          <void index="8"> 
           <double>2.0</double> 
          </void> 
          <void index="9"> 
           <double>-1.0</double> 
          </void> 
         </array> 
        </void> 
        <void method="addLayoutComponent"> 
         <object idref="JLabel0"/> 
         <object class="info.clearthought.layout.TableLayoutConstraints"> 
          <int>1</int> 
          <int>1</int> 
          <int>1</int> 
          <int>1</int> 
          <int>2</int> 
          <int>2</int> 
         </object> 
        </void> 
        <void method="addLayoutComponent"> 
         <object idref="JLabel1"/> 
         <object class="info.clearthought.layout.TableLayoutConstraints"> 
          <int>1</int> 
          <int>3</int> 
          <int>1</int> 
          <int>3</int> 
          <int>2</int> 
          <int>2</int> 
         </object> 
        </void> 
        <void method="addLayoutComponent"> 
         <object idref="JComboBox0"/> 
         <object class="info.clearthought.layout.TableLayoutConstraints"> 
          <int>3</int> 
          <int>3</int> 
          <int>3</int> 
          <int>3</int> 
          <int>2</int> 
          <int>2</int> 
         </object> 
        </void> 
        <void method="addLayoutComponent"> 
         <object idref="JLabel2"/> 
         <object class="info.clearthought.layout.TableLayoutConstraints"> 
          <int>1</int> 
          <int>5</int> 
          <int>1</int> 
          <int>5</int> 
          <int>2</int> 
          <int>2</int> 
         </object> 
        </void> 
        <void method="addLayoutComponent"> 
         <object idref="JComboBox1"/> 
         <object class="info.clearthought.layout.TableLayoutConstraints"> 
          <int>3</int> 
          <int>5</int> 
          <int>3</int> 
          <int>5</int> 
          <int>2</int> 
          <int>2</int> 
         </object> 
        </void> 
       </object> 
      </void> 
      <void property="name"> 
       <string>GlobalPanel</string> 
      </void> 
     </object> 
    </void> 
   </array> 
  </void> 
  <void property="physicalController"> 
   <object class="org.strandz.core.applichousing.PictToolBarController"/> 
  </void> 
  <void property="statusBar"> 
   <object class="org.strandz.core.applichousing.NodeStatusBar"/> 
  </void> 
 </object> 
</java> 
